<?xml version="1.0" encoding="UTF-8"?>
<vivadoHLSLog:LogRoot xmlns:vivadoHLSLog="www.xilinx.com/vivadoHLSLog">
  <errorLogs>
    <logs>
      <packageLog/>
    </logs>
  </errorLogs>
  <warningLogs>
    <logs>
      <packageLog>
        <logs message="WARNING: [Timing 38-242] The property HD.CLK_SRC of clock port &quot;ap_clk&quot; is not set. In out-of-context mode, this prevents timing estimation for clock delay/skew&#xA;Resolution: Set the HD.CLK_SRC property of the out-of-context port to the location of the clock buffer instance in the top-level design" projectName="HLS" solutionName="solution1" date="2019-12-27T12:20:22.672+0900" type="Warning"/>
        <logs message="WARNING: [Timing 38-242] The property HD.CLK_SRC of clock port &quot;ap_clk&quot; is not set. In out-of-context mode, this prevents timing estimation for clock delay/skew&#xA;Resolution: Set the HD.CLK_SRC property of the out-of-context port to the location of the clock buffer instance in the top-level design" projectName="HLS" solutionName="solution1" date="2019-12-27T12:20:04.622+0900" type="Warning"/>
        <logs message="WARNING: [Route 35-198] Port &quot;input_data_tdata[6]&quot; does not have an associated HD.PARTPIN_LOCS, which will prevent the partial routing of the signal &quot;input_data_tdata[6]&quot;. Without this partial route, timing analysis to/from this port will not be accurate, and no routing information for this port can be exported.&#xA;Phase 1 Build RT Design | Checksum: 169f9edbe&#xA;&#xA;&#xA;Time (s): cpu = 00:00:23 ; elapsed = 00:00:16 . Memory (MB): peak = 2817.156 ; gain = 9.008 ; free physical = 2414 ; free virtual = 8350&#xA;Post Restoration Checksum: NetGraph: 823b89e6 NumContArr: e7be63d8 Constraints: 0 Timing: 0&#xA;&#xA;&#xA;Phase 2 Router Initialization&#xA;&#xA;&#xA;Phase 2.1 Create Timer&#xA;Phase 2.1 Create Timer | Checksum: 169f9edbe&#xA;&#xA;&#xA;Time (s): cpu = 00:00:24 ; elapsed = 00:00:17 . Memory (MB): peak = 2817.156 ; gain = 9.008 ; free physical = 2417 ; free virtual = 8354&#xA;&#xA;&#xA;Phase 2.2 Fix Topology Constraints&#xA;Phase 2.2 Fix Topology Constraints | Checksum: 169f9edbe&#xA;&#xA;&#xA;Time (s): cpu = 00:00:24 ; elapsed = 00:00:17 . Memory (MB): peak = 2817.156 ; gain = 9.008 ; free physical = 2399 ; free virtual = 8335&#xA;&#xA;&#xA;Phase 2.3 Pre Route Cleanup&#xA;Phase 2.3 Pre Route Cleanup | Checksum: 169f9edbe&#xA;&#xA;&#xA;Time (s): cpu = 00:00:24 ; elapsed = 00:00:17 . Memory (MB): peak = 2817.156 ; gain = 9.008 ; free physical = 2399 ; free virtual = 8335&#xA; Number of Nodes with overlaps = 0&#xA;&#xA;&#xA;Phase 2.4 Update Timing&#xA;Phase 2.4 Update Timing | Checksum: 1f7366cde&#xA;&#xA;&#xA;Time (s): cpu = 00:00:30 ; elapsed = 00:00:20 . Memory (MB): peak = 2817.156 ; gain = 9.008 ; free physical = 2375 ; free virtual = 8311" projectName="HLS" solutionName="solution1" date="2019-12-27T12:19:19.605+0900" type="Warning"/>
        <logs message="WARNING: [Route 35-198] Port &quot;input_data_tdata[7]&quot; does not have an associated HD.PARTPIN_LOCS, which will prevent the partial routing of the signal &quot;input_data_tdata[7]&quot;. Without this partial route, timing analysis to/from this port will not be accurate, and no routing information for this port can be exported." projectName="HLS" solutionName="solution1" date="2019-12-27T12:19:04.728+0900" type="Warning"/>
        <logs message="WARNING: [Route 35-198] Port &quot;input_data_tdata[1]&quot; does not have an associated HD.PARTPIN_LOCS, which will prevent the partial routing of the signal &quot;input_data_tdata[1]&quot;. Without this partial route, timing analysis to/from this port will not be accurate, and no routing information for this port can be exported." projectName="HLS" solutionName="solution1" date="2019-12-27T12:19:04.726+0900" type="Warning"/>
        <logs message="WARNING: [Route 35-198] Port &quot;input_data_tdata[0]&quot; does not have an associated HD.PARTPIN_LOCS, which will prevent the partial routing of the signal &quot;input_data_tdata[0]&quot;. Without this partial route, timing analysis to/from this port will not be accurate, and no routing information for this port can be exported." projectName="HLS" solutionName="solution1" date="2019-12-27T12:19:04.725+0900" type="Warning"/>
        <logs message="WARNING: [Route 35-198] Port &quot;input_data_tdata[13]&quot; does not have an associated HD.PARTPIN_LOCS, which will prevent the partial routing of the signal &quot;input_data_tdata[13]&quot;. Without this partial route, timing analysis to/from this port will not be accurate, and no routing information for this port can be exported." projectName="HLS" solutionName="solution1" date="2019-12-27T12:19:04.723+0900" type="Warning"/>
        <logs message="WARNING: [Route 35-198] Port &quot;input_data_tdata[14]&quot; does not have an associated HD.PARTPIN_LOCS, which will prevent the partial routing of the signal &quot;input_data_tdata[14]&quot;. Without this partial route, timing analysis to/from this port will not be accurate, and no routing information for this port can be exported." projectName="HLS" solutionName="solution1" date="2019-12-27T12:19:04.721+0900" type="Warning"/>
        <logs message="WARNING: [Route 35-198] Port &quot;input_data_tid[0]&quot; does not have an associated HD.PARTPIN_LOCS, which will prevent the partial routing of the signal &quot;input_data_tid[0]&quot;. Without this partial route, timing analysis to/from this port will not be accurate, and no routing information for this port can be exported." projectName="HLS" solutionName="solution1" date="2019-12-27T12:19:04.720+0900" type="Warning"/>
        <logs message="WARNING: [Route 35-198] Port &quot;input_data_tdata[4]&quot; does not have an associated HD.PARTPIN_LOCS, which will prevent the partial routing of the signal &quot;input_data_tdata[4]&quot;. Without this partial route, timing analysis to/from this port will not be accurate, and no routing information for this port can be exported." projectName="HLS" solutionName="solution1" date="2019-12-27T12:19:04.718+0900" type="Warning"/>
        <logs message="WARNING: [Route 35-198] Port &quot;input_data_tdata[15]&quot; does not have an associated HD.PARTPIN_LOCS, which will prevent the partial routing of the signal &quot;input_data_tdata[15]&quot;. Without this partial route, timing analysis to/from this port will not be accurate, and no routing information for this port can be exported." projectName="HLS" solutionName="solution1" date="2019-12-27T12:19:04.717+0900" type="Warning"/>
        <logs message="WARNING: [Route 35-198] Port &quot;input_data_tdata[9]&quot; does not have an associated HD.PARTPIN_LOCS, which will prevent the partial routing of the signal &quot;input_data_tdata[9]&quot;. Without this partial route, timing analysis to/from this port will not be accurate, and no routing information for this port can be exported." projectName="HLS" solutionName="solution1" date="2019-12-27T12:19:04.715+0900" type="Warning"/>
        <logs message="WARNING: [Route 35-198] Port &quot;input_data_tdata[5]&quot; does not have an associated HD.PARTPIN_LOCS, which will prevent the partial routing of the signal &quot;input_data_tdata[5]&quot;. Without this partial route, timing analysis to/from this port will not be accurate, and no routing information for this port can be exported." projectName="HLS" solutionName="solution1" date="2019-12-27T12:19:04.714+0900" type="Warning"/>
        <logs message="WARNING: [Route 35-198] Port &quot;input_data_tdata[3]&quot; does not have an associated HD.PARTPIN_LOCS, which will prevent the partial routing of the signal &quot;input_data_tdata[3]&quot;. Without this partial route, timing analysis to/from this port will not be accurate, and no routing information for this port can be exported." projectName="HLS" solutionName="solution1" date="2019-12-27T12:19:04.712+0900" type="Warning"/>
        <logs message="WARNING: [Route 35-198] Port &quot;input_data_tdata[2]&quot; does not have an associated HD.PARTPIN_LOCS, which will prevent the partial routing of the signal &quot;input_data_tdata[2]&quot;. Without this partial route, timing analysis to/from this port will not be accurate, and no routing information for this port can be exported." projectName="HLS" solutionName="solution1" date="2019-12-27T12:19:04.711+0900" type="Warning"/>
        <logs message="WARNING: [Route 35-198] Port &quot;input_data_tdata[12]&quot; does not have an associated HD.PARTPIN_LOCS, which will prevent the partial routing of the signal &quot;input_data_tdata[12]&quot;. Without this partial route, timing analysis to/from this port will not be accurate, and no routing information for this port can be exported." projectName="HLS" solutionName="solution1" date="2019-12-27T12:19:04.710+0900" type="Warning"/>
        <logs message="WARNING: [Route 35-198] Port &quot;input_data_tdata[10]&quot; does not have an associated HD.PARTPIN_LOCS, which will prevent the partial routing of the signal &quot;input_data_tdata[10]&quot;. Without this partial route, timing analysis to/from this port will not be accurate, and no routing information for this port can be exported." projectName="HLS" solutionName="solution1" date="2019-12-27T12:19:04.708+0900" type="Warning"/>
        <logs message="WARNING: [Route 35-198] Port &quot;input_data_tdest[0]&quot; does not have an associated HD.PARTPIN_LOCS, which will prevent the partial routing of the signal &quot;input_data_tdest[0]&quot;. Without this partial route, timing analysis to/from this port will not be accurate, and no routing information for this port can be exported." projectName="HLS" solutionName="solution1" date="2019-12-27T12:19:04.707+0900" type="Warning"/>
        <logs message="WARNING: [Route 35-198] Port &quot;input_data_tdata[8]&quot; does not have an associated HD.PARTPIN_LOCS, which will prevent the partial routing of the signal &quot;input_data_tdata[8]&quot;. Without this partial route, timing analysis to/from this port will not be accurate, and no routing information for this port can be exported." projectName="HLS" solutionName="solution1" date="2019-12-27T12:19:04.705+0900" type="Warning"/>
        <logs message="WARNING: [Route 35-198] Port &quot;input_data_tdata[11]&quot; does not have an associated HD.PARTPIN_LOCS, which will prevent the partial routing of the signal &quot;input_data_tdata[11]&quot;. Without this partial route, timing analysis to/from this port will not be accurate, and no routing information for this port can be exported." projectName="HLS" solutionName="solution1" date="2019-12-27T12:19:04.703+0900" type="Warning"/>
        <logs message="WARNING: [Route 35-198] Port &quot;s_axi_AXILiteS_bready&quot; does not have an associated HD.PARTPIN_LOCS, which will prevent the partial routing of the signal &quot;s_axi_AXILiteS_bready&quot;. Without this partial route, timing analysis to/from this port will not be accurate, and no routing information for this port can be exported." projectName="HLS" solutionName="solution1" date="2019-12-27T12:19:04.701+0900" type="Warning"/>
        <logs message="WARNING: [Route 35-198] Port &quot;input_data_tkeep[0]&quot; does not have an associated HD.PARTPIN_LOCS, which will prevent the partial routing of the signal &quot;input_data_tkeep[0]&quot;. Without this partial route, timing analysis to/from this port will not be accurate, and no routing information for this port can be exported." projectName="HLS" solutionName="solution1" date="2019-12-27T12:19:04.700+0900" type="Warning"/>
      </packageLog>
    </logs>
  </warningLogs>
</vivadoHLSLog:LogRoot>
